pcservices/__init__.py
pcservices/campaign/__init__.py
pcservices/campaign/filters.py
pcservices/campaign/utils.py
pcservices/campaign/validator.py
pcservices/data/__init__.py
pcservices/data/connectors.py
pcservices/data/dataConnector.py
pcservices/data/utils.py
pcservices/pyspark/__init__.py
pcservices/pyspark/toolkit.py
pcservices/spark_helpers.py
pcservices-0.1.3.dist-info/METADATA
pcservices-0.1.3.dist-info/WHEEL
pcservices-0.1.3.dist-info/RECORD
