Metadata-Version: 2.3
Name: pcservices
Version: 0.1.3
Summary: Utility functions for Spark and BigQuery
License: MIT
Author: Gang Huang
Author-email: gang.huang@loblaw.ca
Requires-Python: >=3.10,<4.0
Classifier: License :: OSI Approved :: MIT License
Classifier: Programming Language :: Python :: 3
Classifier: Programming Language :: Python :: 3.10
Classifier: Programming Language :: Python :: 3.11
Classifier: Programming Language :: Python :: 3.12
Classifier: Programming Language :: Python :: 3.13
Requires-Dist: google-cloud-storage (>=2.11.0,<3.0.0)
Requires-Dist: pandas (>=2.2.0)
Requires-Dist: pyspark (>=3.5.0,<4.0.0)
